global_ddm/__init__.py
global_ddm/ddm_5km.nc
global_ddm-1.0.3.dist-info/LICENSE
global_ddm-1.0.3.dist-info/WHEEL
global_ddm-1.0.3.dist-info/METADATA
global_ddm-1.0.3.dist-info/RECORD
