Metadata-Version: 2.1
Name: global_ddm
Version: 1.0.3
Summary: global digit distance model
Author: suozihao
Requires-Python: >=3.6
Classifier: License :: OSI Approved :: MIT License
Requires-Dist: numpy
Requires-Dist: netCDF4
